{
    "uuid": [
        {
            "value": "19d9dcbc-3122-4993-b564-7f33e45302c3"
        }
    ],
    "langcode": [
        {
            "value": "en"
        }
    ],
    "uid": [
        {
            "target_type": "user",
            "target_uuid": "95f85f10-89a1-4110-b3bb-d31c8d4d0c47"
        }
    ],
    "filename": [
        {
            "value": "dummyfile4727559170_5e638650f3_b.jpg.jpg"
        }
    ],
    "uri": [
        {
            "value": "public:\/\/dummyfile4727559170_5e638650f3_b.jpg_0.jpg"
        }
    ],
    "filemime": [
        {
            "value": "image\/jpeg"
        }
    ],
    "filesize": [
        {
            "value": 273154
        }
    ],
    "status": [
        {
            "value": true
        }
    ],
    "created": [
        {
            "value": "2020-03-08T15:34:20+00:00",
            "format": "Y-m-d\\TH:i:sP"
        }
    ],
    "changed": [
        {
            "value": "2020-03-08T15:34:20+00:00",
            "format": "Y-m-d\\TH:i:sP"
        }
    ]
}