{
    "uuid": [
        {
            "value": "93a7877c-d81e-4d9f-be40-ac4ce7526ba1"
        }
    ],
    "langcode": [
        {
            "value": "en"
        }
    ],
    "uid": [
        {
            "target_type": "user",
            "target_uuid": "e5903b2c-729c-41a4-ac1a-bb59a5da7d29"
        }
    ],
    "filename": [
        {
            "value": "dummyfile4726904809_0a85583b5d_b.jpg.jpg"
        }
    ],
    "uri": [
        {
            "value": "public:\/\/dummyfile4726904809_0a85583b5d_b.jpg_6.jpg"
        }
    ],
    "filemime": [
        {
            "value": "image\/jpeg"
        }
    ],
    "filesize": [
        {
            "value": 308997
        }
    ],
    "status": [
        {
            "value": true
        }
    ],
    "created": [
        {
            "value": "2020-03-08T15:34:20+00:00",
            "format": "Y-m-d\\TH:i:sP"
        }
    ],
    "changed": [
        {
            "value": "2020-03-08T15:34:20+00:00",
            "format": "Y-m-d\\TH:i:sP"
        }
    ]
}